mom_test_py/__init__.py
mom_test_py/main.py
mom_test_py/test_validation.py
mom_test_py/rest/__init__.py
mom_test_py-1.0.6.dist-info/METADATA
mom_test_py-1.0.6.dist-info/WHEEL
mom_test_py-1.0.6.dist-info/top_level.txt
mom_test_py-1.0.6.dist-info/RECORD
