Metadata-Version: 2.1
Name: mom-test-py
Version: 1.0.6
Summary: Helper library for working with tests
Home-page: UNKNOWN
License: UNKNOWN
Platform: UNKNOWN
